{
    "skills": "skills",
    "details": "details",
    "clickOnLinkToSeeDetails": "click on link to see details",
    "toggleDisplay": "toggle display of detailed skills",
    "informations": "Informations",
    "wikipediaExtract": "Wikipedia extract",
    "reference": "no reference | one reference | {count} references",
    "about": "about",
    "title": "Title",
    "toolinfomap" : "tools",
    "entity": "Entity",
    "methods": "capabilities",
    "miscellaneous": "Languages",
    "errorExtractFail": "Sorry, data fetch failed for this tool",
    "baseURLWiki": "https://en.wikipedia.org/w/api.php?format=json&action=query&prop=extracts&exintro&explaintext&redirects=1&origin=*&titles=",
    "miscellaneousList": [
        "English B2",
        "Russian A2",
        "Dutch A1",
        "Danish A1"
    ],
    "workflowList": [
        "Ability to adapt",
        "Teamwork",
        "Autonomy",
        "Sense of responsibility",
        "Strength of proposal",
        "Project management"
    ],
        "toolsInfoMap": {

        }
    }
